pyshifu/__init__.py
pyshifu/shifu.py
pyshifu/core/__init__.py
pyshifu/core/enums.py
pyshifu/core/shell.py
pyshifu/core/exception/__init__.py
pyshifu/core/exception/base_exception.py
pyshifu/core/exception/field_exception.py
pyshifu/core/exception/invalid_parameter_exception.py
pyshifu/core/tests/__init__.py
pyshifu/java/bin/driver_test.sh
pyshifu/java/bin/shifu
pyshifu/java/bin/shifu_bash_completion.sh
pyshifu/java/bin/shifutest
pyshifu/java/conf/shifuconfig
pyshifu/java/example/cancer-judgement/DataStore/DataSet1/.pig_header
pyshifu/java/example/cancer-judgement/DataStore/DataSet1/part-00
pyshifu/java/example/cancer-judgement/DataStore/EvalSet1/.pig_header
pyshifu/java/example/cancer-judgement/DataStore/EvalSet1/part-00
pyshifu/java/example/cancer-judgement/DataStore/Full_data/data.dat
pyshifu/java/example/cancer-judgement/ModelStore/ModelSet1/ColumnConfig.json
pyshifu/java/example/cancer-judgement/ModelStore/ModelSet1/ModelConfig.json
pyshifu/java/example/cancer-judgement/ModelStore/ModelSet1/pr_curve.xlsx
pyshifu/java/example/cancer-judgement/ModelStore/ModelSet2/ColumnConfig.json
pyshifu/java/example/cancer-judgement/ModelStore/ModelSet2/ModelConfig.json
pyshifu/java/example/cancer-judgement/ModelStore/ModelSet3/ColumnConfig.json
pyshifu/java/example/cancer-judgement/ModelStore/ModelSet3/ModelConfig.json
pyshifu/java/lib/akka-actor_2.10-2.1.1.jar
pyshifu/java/lib/antlr-2.7.7.jar
pyshifu/java/lib/antlr-runtime-3.4.jar
pyshifu/java/lib/automaton-1.11-8.jar
pyshifu/java/lib/commons-cli-1.2.jar
pyshifu/java/lib/commons-codec-1.6.jar
pyshifu/java/lib/commons-collections-3.2.2.jar
pyshifu/java/lib/commons-compress-1.5.jar
pyshifu/java/lib/commons-configuration-1.6.jar
pyshifu/java/lib/commons-httpclient-3.1.jar
pyshifu/java/lib/commons-io-2.4.jar
pyshifu/java/lib/commons-jexl-2.1.1.jar
pyshifu/java/lib/commons-lang-2.5.jar
pyshifu/java/lib/commons-lang3-3.3.2.jar
pyshifu/java/lib/commons-logging-1.1.1.jar
pyshifu-0.0.8.dist-info/DESCRIPTION.rst
pyshifu-0.0.8.dist-info/METADATA
pyshifu-0.0.8.dist-info/RECORD
pyshifu-0.0.8.dist-info/WHEEL
pyshifu-0.0.8.dist-info/metadata.json
pyshifu-0.0.8.dist-info/top_level.txt
