Metadata-Version: 2.0
Name: pyshifu
Version: 0.0.8
Summary: An end-to-end machine learning and data mining framework on Hadoop.
Home-page: https://github.com/shifuml/pyshifu
Author: Wu Haifeng
Author-email: wuhaifengdhu@163.com
License: UNKNOWN
Platform: UNKNOWN
Requires-Dist: six (>=1.11.0)
